hyperxar/__init__.py
hyperxar/core.py
hyperxar-0.2.0.dist-info/METADATA
hyperxar-0.2.0.dist-info/WHEEL
hyperxar-0.2.0.dist-info/top_level.txt
hyperxar-0.2.0.dist-info/RECORD
