Metadata-Version: 2.4
Name: hyperxar
Version: 0.2.0
Summary: Python3 Modul zum Kopieren, Komprimieren, Extrahieren und ISO-Erstellen mit Fortschrittsanzeige
Home-page: https://github.com/MultiCodex/hyperxar
Author: Calvin Ronksley
Author-email: youremail@example.com
Classifier: Programming Language :: Python :: 3
Classifier: License :: OSI Approved :: MIT License
Classifier: Operating System :: OS Independent
Requires-Python: >=3.10
Requires-Dist: tqdm
Requires-Dist: py7zr
Dynamic: author
Dynamic: author-email
Dynamic: classifier
Dynamic: description
Dynamic: description-content-type
Dynamic: home-page
Dynamic: requires-dist
Dynamic: requires-python
Dynamic: summary
